si_prefix/__init__.py
si_prefix/_version.py
si_prefix-1.3.3.dist-info/LICENSE.md
si_prefix-1.3.3.dist-info/METADATA
si_prefix-1.3.3.dist-info/WHEEL
si_prefix-1.3.3.dist-info/top_level.txt
si_prefix-1.3.3.dist-info/RECORD
