Metadata-Version: 2.1
Name: si-prefix
Version: 1.3.3
Summary: Functions for formatting numbers according to SI standards.
Author-email: Christian Fobel <christian@fobel.net>
License: BSD-3
Project-URL: homepage, https://github.com/cfobel/si-prefix
Keywords: si,prefix,format,number,precision
License-File: LICENSE.md
Provides-Extra: testing
Requires-Dist: pytest ; extra == 'testing'
Requires-Dist: pytest-cov ; extra == 'testing'
Requires-Dist: black ; extra == 'testing'
Requires-Dist: flake8 ; extra == 'testing'
Requires-Dist: flake8-pyproject ; extra == 'testing'
Requires-Dist: isort ; extra == 'testing'
